pyscheduling/BaseConstraints.py
pyscheduling/FS/FS_CSP.ipynb
pyscheduling/FS/FS_methods.py
pyscheduling/FS/FlowShop.py
pyscheduling/FS/FmCmax.py
pyscheduling/FS/FmSijkCmax.py
pyscheduling/FS/FmriSijkCmax.py
pyscheduling/FS/FmriSijkwiCi.py
pyscheduling/FS/FmriSijkwiFi.py
pyscheduling/FS/FmridiSijkwiTi.py
pyscheduling/FS/__init__.py
pyscheduling/JS/Constraints.py
pyscheduling/JS/JS_methods.py
pyscheduling/JS/JmCmax.py
pyscheduling/JS/JmriSijkCmax.py
pyscheduling/JS/JmriSijkwiCi.py
pyscheduling/JS/JmriSijkwiFi.py
pyscheduling/JS/JmridiSijkwiTi.py
pyscheduling/JS/JmriwiTi.py
pyscheduling/JS/JobShop.py
pyscheduling/JS/Jobshop_CSP.ipynb
pyscheduling/JS/Jobshop_MILP.ipynb
pyscheduling/JS/__init__.py
pyscheduling/PMSP/PM_methods.py
pyscheduling/PMSP/ParallelMachines.py
pyscheduling/PMSP/RmSijkCmax.py
pyscheduling/PMSP/RmriSijkCmax.py
pyscheduling/PMSP/RmriSijkWiCi.py
pyscheduling/PMSP/RmriSijkWiFi.py
pyscheduling/PMSP/RmridiSijkWiTi.py
pyscheduling/PMSP/Testing PMSP.ipynb
pyscheduling/PMSP/__init__.py
pyscheduling/PMSP/interface.py
pyscheduling/Problem.py
pyscheduling/SMSP/Constraints.py
pyscheduling/SMSP/SMSP_tests.ipynb
pyscheduling/SMSP/SM_CSP.ipynb
pyscheduling/SMSP/SM_methods.py
pyscheduling/SMSP/SingleMachine.py
pyscheduling/SMSP/__init__.py
pyscheduling/SMSP/interface.py
pyscheduling/SMSP/riPrecLmax.py
pyscheduling/SMSP/rihiCi.py
pyscheduling/SMSP/risijCmax.py
pyscheduling/SMSP/risijwiCi.py
pyscheduling/SMSP/risijwiFi.py
pyscheduling/SMSP/risijwiTi.py
pyscheduling/SMSP/riwiCi.py
pyscheduling/SMSP/riwiTi.py
pyscheduling/SMSP/sijCmax.py
pyscheduling/SMSP/sijwiTi.py
pyscheduling/SMSP/wiCi.py
pyscheduling/SMSP/wiTi.py
pyscheduling/__init__.py
pyscheduling/benchmark.py
pyscheduling/pyscheduling.py
pyscheduling-0.1.8.dist-info/LICENSE.md
pyscheduling-0.1.8.dist-info/METADATA
pyscheduling-0.1.8.dist-info/WHEEL
pyscheduling-0.1.8.dist-info/RECORD
