Metadata-Version: 2.1
Name: pyscheduling
Version: 0.1.8
Summary: THE python package to solve scheduling problems
License: CC-BY-NC-ND-4.0
Author: Amine ATHMANI
Requires-Python: >=3.8,<4.0
Classifier: License :: Other/Proprietary License
Classifier: Programming Language :: Python :: 3
Classifier: Programming Language :: Python :: 3.8
Classifier: Programming Language :: Python :: 3.9
Classifier: Programming Language :: Python :: 3.10
Classifier: Programming Language :: Python :: 3.11
Requires-Dist: networkx (>=3.0,<4.0)
Requires-Dist: numpy (>=1.24.2,<2.0.0)
Requires-Dist: plotly (>=5.13.1,<6.0.0)
